examples/memory/sv/dual_port_ram.sv
// Simple Dual-Port Block RAM with One Clock
// File: dual_port_ram.v

module dual_port_ram (clk,ena,enb,wea,addra,addrb,dia,dob);

input clk,ena,enb,wea;
input [9:0] addra,addrb;
input [15:0] dia;
output [15:0] dob;
reg [15:0] ram [1023:0];
// reg [15:0] doa,dob;
reg [15:0] dob;

always @(posedge clk) begin
if (ena) begin
if (wea)
ram[addra] <= dia;
end
end

always @(posedge clk) begin
if (enb)
dob <= ram[addrb];
end

endmodule

waveforms/dual_port_ram_v.vcd
$version Generated by VerilatedVcd $end
$timescale 1ps $end
 $scope module TOP $end
  $var wire 1 # clk $end
  $var wire 1 $ ena $end
  $var wire 1 % enb $end
  $var wire 1 & wea $end
  $var wire 10 ' addra [9:0] $end
  $var wire 10 ( addrb [9:0] $end
  $var wire 16 ) dia [15:0] $end
  $var wire 16 * dob [15:0] $end
  $scope module dual_port_ram $end
   $var wire 1 # clk $end
   $var wire 1 $ ena $end
   $var wire 1 % enb $end
   $var wire 1 & wea $end
   $var wire 10 ' addra [9:0] $end
   $var wire 10 ( addrb [9:0] $end
   $var wire 16 ) dia [15:0] $end
   $var wire 16 * dob [15:0] $end
  $upscope $end
 $upscope $end
$enddefinitions $end


#0
0#
1$
0%
1&
b0000000101 '
b0000000000 (
b1010101111001101 )
b0000000000000000 *
#1
1#
#2
0#
0$
1%
0&
b0000000000 '
b0000000101 (
b0000000000000000 )
#3
1#
b1010101111001101 *
#4
0#
0%
#5
1#
#6
0#
1$
1%
1&
b0000001010 '
b0000001010 (
b0001001000110100 )
#7
1#
b0000000000000000 *
#8
0#
0$
0&
b0000000000 '
b0000000000000000 )
#9
1#
b0001001000110100 *
#10
0#
1$
0%
1&
b0000011111 '
b0000000000 (
b1101111010101101 )
#11
1#
#12
0#
0$
1%
0&
b0000000000 '
b0000000101 (
b0000000000000000 )
#13
1#
b1010101111001101 *
