examples/sequential/sv/lfsr.sv
// note XOR mask starts at bit 0; which may
// be shifted from mathematician's notation.

module lfsr (input clk
    , input reset_i
    , input yumi_i
    , output logic [32-1:0] o
    );

  logic [32-1:0] o_r, o_n, xor_mask;

  assign o = o_r;

  // auto mask value
  assign xor_mask = (1 << 31) | (1 << 29) | (1 << 26) | (1 << 25);

  always @(posedge clk)
    begin
      if (reset_i)
        o_r <= (32) ' (1);
      else if (yumi_i)
        o_r <= o_n;
    end

  assign o_n = (o_r >> 1) ^ ({32 {o_r[0]}} & xor_mask);
   

endmodule // bsg_lfsr

waveforms/lfsr.vcd
$timescale 1ps $end
$scope module lfsr $end
$var wire 1 ! reset_i $end
$var wire 1 " yumi_i $end
$var wire 32 # o $end
$upscope $end
$enddefinitions $end
#0
$dumpvars
b1 !
b0 "
b00000000000000000000000000000001 #
$end
#0
b1 !
b0 "
b00000000000000000000000000000001 #
#1
b0 !
b1 "
b10100110000000000000000000000000 #
#2
b0 !
b1 "
b01010011000000000000000000000000 #
#3
b0 !
b1 "
b00101001100000000000000000000000 #
#4
b0 !
b1 "
b00010100110000000000000000000000 #
#5
b0 !
b1 "
b00001010011000000000000000000000 #
#6
b0 !
b1 "
b00000101001100000000000000000000 #
#7
b0 !
b1 "
b00000010100110000000000000000000 #
#8
b0 !
b1 "
b00000001010011000000000000000000 #
#9
b0 !
b1 "
b00000000101001100000000000000000 #
#10
b0 !
b1 "
b00000000010100110000000000000000 #
#11
b0 !
b1 "
b00000000001010011000000000000000 #
#12
b0 !
b1 "
b00000000000101001100000000000000 #
#13
b0 !
b1 "
b00000000000010100110000000000000 #
#14
b0 !
b1 "
b00000000000001010011000000000000 #
#15
b0 !
b1 "
b00000000000000101001100000000000 #
#16
b0 !
b1 "
b00000000000000010100110000000000 #
