examples/sequential/sv/pattern_detector.sv
module det_110101 ( input clk,
                  	 input rstn,
                  	 input in,
                  	 output out );

  parameter IDLE 	= 0,
  			S1 		= 1,
  			S11 	= 2,
  			S110 	= 3,
  			S1101 	= 4,
  			S11010 	= 5,
  			S110101 = 6;

  reg [2:0] cur_state, next_state;

  assign out = cur_state == S110101 ? 1 : 0;

  always @ (posedge clk) begin
    if (!rstn)
      	cur_state <= IDLE;
     else
     	cur_state <= next_state;
  end

  always @ (cur_state or in) begin
    case (cur_state)
      IDLE : begin
        if (in) next_state = S1;
        else 	next_state = IDLE;
      end

      S1: begin
        if (in) next_state = S11;
        else 	next_state = IDLE;
      end

      S11: begin
        if (!in) next_state = S110;
        else 	next_state = S11;
      end

      S110 : begin
        if (in) next_state = S1101;
        else 	next_state = IDLE;
      end

      S1101 : begin
        if (!in) next_state = S11010;
        else 	next_state = IDLE;
      end

      S11010: begin
        if (in) next_state = S110101;
        else 	next_state = IDLE;
      end

      S110101: begin
        if (in) next_state = S1;
        else 	next_state = IDLE; 		// Bug 2
      end
    endcase
  end
endmodule

waveforms/pattern_detector_verilator.vcd
$version Generated by VerilatedVcd $end
$timescale 1ps $end
 $scope module TOP $end
  $var wire 1 # clk $end
  $var wire 1 $ rstn $end
  $var wire 1 % in $end
  $var wire 1 & out $end
  $scope module det_110101 $end
   $var wire 1 # clk $end
   $var wire 1 $ rstn $end
   $var wire 1 % in $end
   $var wire 1 & out $end
   $var wire 32 ) IDLE [31:0] $end
   $var wire 32 * S1 [31:0] $end
   $var wire 32 + S11 [31:0] $end
   $var wire 32 , S110 [31:0] $end
   $var wire 32 - S1101 [31:0] $end
   $var wire 32 . S11010 [31:0] $end
   $var wire 32 / S110101 [31:0] $end
   $var wire 3 ' cur_state [2:0] $end
   $var wire 3 ( next_state [2:0] $end
  $upscope $end
 $upscope $end
$enddefinitions $end


#0
0#
0$
0%
0&
b000 '
b000 (
b00000000000000000000000000000000 )
b00000000000000000000000000000001 *
b00000000000000000000000000000010 +
b00000000000000000000000000000011 ,
b00000000000000000000000000000100 -
b00000000000000000000000000000101 .
b00000000000000000000000000000110 /
#1
1#
#2
0#
1$
1%
b001 (
#3
1#
b001 '
b010 (
#4
0#
#5
1#
b010 '
#6
0#
0%
b011 (
#7
1#
b011 '
b000 (
#8
0#
1%
b100 (
#9
1#
b100 '
b000 (
#10
0#
0%
b101 (
#11
1#
b101 '
b000 (
#12
0#
1%
b110 (
#13
1#
1&
b110 '
b001 (
#14
0#
#15
1#
0&
b001 '
b010 (
#16
0#
0%
b000 (
#17
1#
b000 '
#18
0#
0$
1%
b001 (
