examples/combinational/sv/ripple_carry_adder.sv
// Adapted from BaseJump STL — bsg_misc/bsg_adder_ripple_carry.sv
//   https://github.com/bespoke-silicon-group/basejump_stl
//   Solderpad Hardware License v0.51 (Apache-2.0-based). Copyright 2016
//   Michael B. Taylor / BaseJump STL contributors.
// Adapted for self-contained Verilator use (bsg_defines/macros stripped, concrete
// parameter default); the adder logic is unchanged.
//
// width_p default set to 8 for Verilator testing.
module bsg_adder_ripple_carry #(parameter width_p = 8)
  (
    input  [width_p-1:0] a_i,
    input  [width_p-1:0] b_i,
    output logic [width_p-1:0] s_o,
    output logic c_o
  );

  assign {c_o, s_o} = a_i + b_i;

endmodule

waveforms/ripple_carry_adder.vcd
$timescale 1ps $end
$scope module bsg_adder_ripple_carry $end
$var wire 8 ! a_i $end
$var wire 8 " b_i $end
$var wire 8 # s_o $end
$var wire 1 $ c_o $end
$upscope $end
$enddefinitions $end
#0
$dumpvars
b00000000 !
b00000000 "
b00000000 #
b0 $
$end
#0
b00000000 !
b00000000 "
b00000000 #
b0 $
#1
b00000001 !
b00000010 "
b00000011 #
b0 $
#2
b01111111 !
b00000001 "
b10000000 #
b0 $
#3
b11111111 !
b00000000 "
b11111111 #
b0 $
#4
b11111111 !
b00000001 "
b00000000 #
b1 $
#5
b10000000 !
b10000000 "
b00000000 #
b1 $
#6
b11001000 !
b01100100 "
b00101100 #
b1 $
#7
b11111111 !
b11111111 "
b11111110 #
b1 $
#8
b00001111 !
b11110000 "
b11111111 #
b0 $
